MANIFEST.in
README.rst
setup.py
bin/django-nosetests.py
docs/Makefile
docs/changes.rst
docs/conf.py
docs/index.rst
docs/make.bat
docs/running_tests.rst
docs/writing_tests.rst
tddspry/__init__.py
tddspry/cases.py
tddspry/utils.py
tddspry.egg-info/PKG-INFO
tddspry.egg-info/SOURCES.txt
tddspry.egg-info/dependency_links.txt
tddspry.egg-info/entry_points.txt
tddspry.egg-info/requires.txt
tddspry.egg-info/top_level.txt
tddspry/django/__init__.py
tddspry/django/cases.py
tddspry/django/decorators.py
tddspry/django/runner.py
tddspry/django/settings.py
tddspry/django/helpers/__init__.py
tddspry/django/helpers/auth.py
tddspry/django/helpers/registration.py
tddspry/noseplugins/__init__.py
tddspry/noseplugins/djangoplugin.py