Metadata-Version: 1.1
Name: tddspry
Version: 0.4-beta
Summary: Collection of test cases and additional helpers to test Django applications with nose library.
Home-page: http://github.com/playpauseandstop/tddspry
Author: Igor Davydenko
Author-email: playpauseandstop@gmail.com
License: UNKNOWN
Keywords: django nose tdd testing tests twill
Platform: UNKNOWN
Classifier: Development Status :: 4 - Beta
Classifier: Environment :: Web Environment
Classifier: Framework :: Django
Classifier: License :: OSI Approved :: BSD License
Classifier: Topic :: Software Development :: Testing
Requires: Django (>= 1.0)
Requires: nose (>= 0.11.0)
Requires: twill (>= 0.9)
